phishme_intelligence/__init__.py
phishme_intelligence/__main__.py
phishme_intelligence/__pycache__/__init__.cpython-37.pyc
phishme_intelligence/core/__init__.py
phishme_intelligence/core/brand_intelligence.py
phishme_intelligence/core/config_check.py
phishme_intelligence/core/exceptions.py
phishme_intelligence/core/intelligence.py
phishme_intelligence/core/metadata.py
phishme_intelligence/core/phishme.py
phishme_intelligence/core/rest_api.py
phishme_intelligence/core/sqlite.py
phishme_intelligence/core/supported_integrations.py
phishme_intelligence/core/syslog.py
phishme_intelligence/core/__pycache__/__init__.cpython-37.pyc
phishme_intelligence/core/__pycache__/brand_intelligence.cpython-37.pyc
phishme_intelligence/core/__pycache__/config_check.cpython-37.pyc
phishme_intelligence/core/__pycache__/exceptions.cpython-37.pyc
phishme_intelligence/core/__pycache__/intelligence.cpython-37.pyc
phishme_intelligence/core/__pycache__/metadata.cpython-37.pyc
phishme_intelligence/core/__pycache__/phishme.cpython-37.pyc
phishme_intelligence/core/__pycache__/rest_api.cpython-37.pyc
phishme_intelligence/core/__pycache__/supported_integrations.cpython-37.pyc
phishme_intelligence/output/__init__.py
phishme_intelligence/output/base_integration.py
phishme_intelligence/output/manifest.ini
phishme_intelligence/output/__pycache__/__init__.cpython-37.pyc
phishme_intelligence/output/__pycache__/base_integration.cpython-37.pyc
phishme_intelligence/output/generic/__init__.py
phishme_intelligence/output/generic/generic_integration.py
phishme_intelligence/output/generic/pm_cef.py
phishme_intelligence/output/generic/pm_json.py
phishme_intelligence/output/generic/pm_stix.py
phishme_intelligence/output/generic/__pycache__/__init__.cpython-37.pyc
phishme_intelligence/output/generic/__pycache__/generic_integration.cpython-37.pyc
phishme_intelligence/output/generic/__pycache__/pm_cef.cpython-37.pyc
phishme_intelligence/output/generic/__pycache__/pm_json.cpython-37.pyc
phishme_intelligence-4.7.9.dist-info/LICENSE
phishme_intelligence-4.7.9.dist-info/METADATA
phishme_intelligence-4.7.9.dist-info/WHEEL
phishme_intelligence-4.7.9.dist-info/top_level.txt
phishme_intelligence-4.7.9.dist-info/RECORD
