Metadata-Version: 2.1
Name: phishme-intelligence
Version: 4.7.9
Summary: PhishMe Intelligence Integration Library
Home-page: https://www.threathq.com/documentation/display/MAD
Author: PhishMe Intelligence Solutions Engineering
Author-email: support@phishme.com
License: Proprietary
Keywords: phishing threat intelligence
Platform: UNKNOWN
Classifier: Development Status :: 5 - Production/Stable
Classifier: Intended Audience :: Information Technology
Classifier: License :: Free To Use But Restricted
Classifier: Programming Language :: Python :: 2.7
Classifier: Programming Language :: Python :: 3.4
Classifier: Programming Language :: Python :: 3.5
Classifier: Programming Language :: Python :: 3.6
Classifier: Programming Language :: Python :: 3.7
Classifier: Topic :: Security
Requires-Dist: requests (>=2.3)
Requires-Dist: defusedxml (>=0.5.0)
Requires-Dist: six (>=1.11.0)
